{
    "sourceFile": "6_detail/style/style.scss",
    "activeCommit": 0,
    "commits": [
        {
            "activePatchIndex": 4,
            "patches": [
                {
                    "date": 1656100013390,
                    "content": "Index: \n===================================================================\n--- \n+++ \n"
                },
                {
                    "date": 1656100021439,
                    "content": "Index: \n===================================================================\n--- \n+++ \n@@ -1,8 +1,8 @@\n @import \"./_variable\";\r\n @import \"./_general\";\r\n @import \"./_mixin\";\r\n \r\n-@import \"../0_general/style/item\";\r\n+@import \"../../\";\r\n @import \"./activity\";\r\n @import \"./hotel\";\r\n @import \"./restaurant\";\n\\ No newline at end of file\n"
                },
                {
                    "date": 1656100029026,
                    "content": "Index: \n===================================================================\n--- \n+++ \n@@ -1,8 +1,8 @@\n @import \"./_variable\";\r\n @import \"./_general\";\r\n @import \"./_mixin\";\r\n \r\n-@import \"../../\";\r\n+@import \"../../0_general/i\";\r\n @import \"./activity\";\r\n @import \"./hotel\";\r\n @import \"./restaurant\";\n\\ No newline at end of file\n"
                },
                {
                    "date": 1656100037273,
                    "content": "Index: \n===================================================================\n--- \n+++ \n@@ -1,8 +1,8 @@\n @import \"./_variable\";\r\n @import \"./_general\";\r\n @import \"./_mixin\";\r\n \r\n-@import \"../../0_general/i\";\r\n+@import \"../../0_general/style/c\";\r\n @import \"./activity\";\r\n @import \"./hotel\";\r\n @import \"./restaurant\";\n\\ No newline at end of file\n"
                },
                {
                    "date": 1656100042615,
                    "content": "Index: \n===================================================================\n--- \n+++ \n@@ -1,8 +1,8 @@\n @import \"./_variable\";\r\n @import \"./_general\";\r\n @import \"./_mixin\";\r\n \r\n-@import \"../../0_general/style/c\";\r\n+@import \"../../0_general/style/item\";\r\n @import \"./activity\";\r\n @import \"./hotel\";\r\n @import \"./restaurant\";\n\\ No newline at end of file\n"
                }
            ],
            "date": 1656100013390,
            "name": "Commit-0",
            "content": "@import \"./_variable\";\r\n@import \"./_general\";\r\n@import \"./_mixin\";\r\n\r\n@import \"../0_general/style/item\";\r\n@import \"./activity\";\r\n@import \"./hotel\";\r\n@import \"./restaurant\";"
        }
    ]
}